FashionTrendForecasting/__init__.py
FashionTrendForecasting/api/__init__.py
FashionTrendForecasting/api/main.py
FashionTrendForecasting/data_processing/__init__.py
FashionTrendForecasting/data_processing/insert_data.py
FashionTrendForecasting/data_processing/sql_interactions.py
FashionTrendForecasting/trend_analysis/Simple_Model.py
FashionTrendForecasting/trend_analysis/__init__.py
FashionTrendForecasting/trend_analysis/model.py
FashionTrendForecasting-0.1.0.dist-info/LICENSE
FashionTrendForecasting-0.1.0.dist-info/METADATA
FashionTrendForecasting-0.1.0.dist-info/WHEEL
FashionTrendForecasting-0.1.0.dist-info/top_level.txt
FashionTrendForecasting-0.1.0.dist-info/RECORD
