Metadata-Version: 2.1
Name: FashionTrendForecasting
Version: 0.1.0
Summary: A package for predicting fashion trends
Author: Anahit Manukyan, Milena Bazoyan, Lusine Torosyan, Sate Antaranyan
Requires-Python: >=3.12.0
License-File: LICENSE
Requires-Dist: annotated-types ==0.6.0
Requires-Dist: anyio ==4.3.0
Requires-Dist: appnope ==0.1.4
Requires-Dist: argon2-cffi ==23.1.0
Requires-Dist: argon2-cffi-bindings ==21.2.0
Requires-Dist: arrow ==1.3.0
Requires-Dist: asttokens ==2.4.1
Requires-Dist: async-lru ==2.0.4
Requires-Dist: attrs ==23.2.0
Requires-Dist: Babel ==2.15.0
Requires-Dist: beautifulsoup4 ==4.12.3
Requires-Dist: bleach ==6.1.0
Requires-Dist: certifi ==2024.2.2
Requires-Dist: cffi ==1.16.0
Requires-Dist: charset-normalizer ==3.3.2
Requires-Dist: click ==8.1.7
Requires-Dist: comm ==0.2.2
Requires-Dist: contourpy ==1.2.1
Requires-Dist: cycler ==0.12.1
Requires-Dist: debugpy ==1.8.1
Requires-Dist: decorator ==5.1.1
Requires-Dist: defusedxml ==0.7.1
Requires-Dist: executing ==2.0.1
Requires-Dist: Faker ==24.14.0
Requires-Dist: fastapi ==0.110.0
Requires-Dist: fastjsonschema ==2.19.1
Requires-Dist: fonttools ==4.51.0
Requires-Dist: fqdn ==1.5.1
Requires-Dist: h11 ==0.14.0
Requires-Dist: httpcore ==1.0.5
Requires-Dist: httptools ==0.6.1
Requires-Dist: httpx ==0.27.0
Requires-Dist: idna ==3.6
Requires-Dist: ipykernel ==6.29.4
Requires-Dist: ipython ==8.24.0
Requires-Dist: ipywidgets ==8.1.2
Requires-Dist: isoduration ==20.11.0
Requires-Dist: jedi ==0.19.1
Requires-Dist: Jinja2 ==3.1.4
Requires-Dist: joblib ==1.4.0
Requires-Dist: json5 ==0.9.25
Requires-Dist: jsonpointer ==2.4
Requires-Dist: jsonschema ==4.22.0
Requires-Dist: jsonschema-specifications ==2023.12.1
Requires-Dist: jupyter ==1.0.0
Requires-Dist: jupyter-console ==6.6.3
Requires-Dist: jupyter-events ==0.10.0
Requires-Dist: jupyter-lsp ==2.2.5
Requires-Dist: jupyter-client ==8.6.1
Requires-Dist: jupyter-core ==5.7.2
Requires-Dist: jupyter-server ==2.14.0
Requires-Dist: jupyter-server-terminals ==0.5.3
Requires-Dist: jupyterlab ==4.1.8
Requires-Dist: jupyterlab-pygments ==0.3.0
Requires-Dist: jupyterlab-server ==2.27.1
Requires-Dist: jupyterlab-widgets ==3.0.10
Requires-Dist: kiwisolver ==1.4.5
Requires-Dist: MarkupSafe ==2.1.5
Requires-Dist: matplotlib ==3.9.0rc2
Requires-Dist: matplotlib-inline >=0.1.7
Requires-Dist: mistune ==3.0.2
Requires-Dist: nbclient ==0.10.0
Requires-Dist: nbconvert ==7.16.4
Requires-Dist: nbformat ==5.10.4
Requires-Dist: nest-asyncio ==1.6.0
Requires-Dist: notebook ==7.1.3
Requires-Dist: notebook-shim ==0.2.4
Requires-Dist: numpy >=1.26.4
Requires-Dist: overrides ==7.7.0
Requires-Dist: packaging ==24.0
Requires-Dist: pandas >=2.2.1
Requires-Dist: pandocfilters ==1.5.1
Requires-Dist: parso ==0.8.4
Requires-Dist: pexpect ==4.9.0
Requires-Dist: pillow ==10.3.0
Requires-Dist: platformdirs ==4.2.1
Requires-Dist: prometheus-client ==0.20.0
Requires-Dist: prompt-toolkit ==3.0.43
Requires-Dist: psutil ==5.9.8
Requires-Dist: ptyprocess ==0.7.0
Requires-Dist: pure-eval ==0.2.2
Requires-Dist: pycparser ==2.22
Requires-Dist: pydantic ==2.6.4
Requires-Dist: pydantic-core ==2.16.3
Requires-Dist: Pygments ==2.18.0
Requires-Dist: pyparsing ==3.1.2
Requires-Dist: python-dateutil ==2.9.0.post0
Requires-Dist: python-dotenv ==1.0.1
Requires-Dist: python-json-logger ==2.0.7
Requires-Dist: pytz ==2024.1
Requires-Dist: PyYAML ==6.0.1
Requires-Dist: pyzmq ==26.0.3
Requires-Dist: qtconsole ==5.5.2
Requires-Dist: QtPy ==2.4.1
Requires-Dist: referencing ==0.35.1
Requires-Dist: requests ==2.31.0
Requires-Dist: rfc3339-validator ==0.1.4
Requires-Dist: rfc3986-validator ==0.1.1
Requires-Dist: rpds-py ==0.18.1
Requires-Dist: scikit-learn ==1.4.2
Requires-Dist: scipy ==1.13.0
Requires-Dist: seaborn ==0.13.2
Requires-Dist: Send2Trash ==1.8.3
Requires-Dist: six ==1.16.0
Requires-Dist: sniffio ==1.3.1
Requires-Dist: soupsieve ==2.5
Requires-Dist: SQLAlchemy ==2.0.29
Requires-Dist: stack-data ==0.6.3
Requires-Dist: starlette ==0.36.3
Requires-Dist: terminado ==0.18.1
Requires-Dist: threadpoolctl ==3.4.0
Requires-Dist: tinycss2 ==1.3.0
Requires-Dist: tornado ==6.4
Requires-Dist: traitlets ==5.14.3
Requires-Dist: types-python-dateutil ==2.9.0.20240316
Requires-Dist: typing-extensions ==4.10.0
Requires-Dist: tzdata ==2024.1
Requires-Dist: uri-template ==1.3.0
Requires-Dist: urllib3 ==2.2.1
Requires-Dist: uvicorn ==0.29.0
Requires-Dist: uvloop ==0.19.0
Requires-Dist: watchfiles ==0.21.0
Requires-Dist: wcwidth ==0.2.13
Requires-Dist: webcolors ==1.13
Requires-Dist: webencodings ==0.5.1
Requires-Dist: websocket-client ==1.8.0
Requires-Dist: websockets ==12.0
Requires-Dist: widgetsnbextension ==4.0.10
